config/__init__.py
config/config.py
lionhandler-0.3.data/scripts/client
lionhandler-0.3.dist-info/LICENSE
lionhandler-0.3.dist-info/METADATA
lionhandler-0.3.dist-info/WHEEL
lionhandler-0.3.dist-info/top_level.txt
lionhandler-0.3.dist-info/RECORD
