Metadata-Version: 2.1
Name: lionhandler
Version: 0.3
Summary: A client application for handling logging sending to a server
Home-page: https://github.com/thiagolrpinho/loghandler-client
Author: Saulo Leão
Author-email: sleaojr@gmail.com
License: UNKNOWN
Platform: UNKNOWN
Classifier: Programming Language :: Python :: 3
Classifier: License :: OSI Approved :: MIT License
Classifier: Operating System :: OS Independent
